bobwhois.py
kisa.py
kisaBobPkgs.py
newWhoisBobPkgs.py
test_bob8gook.py
testbob8gook.py
whois.py
whoisBobPkgs.py
newWhoisBobPkgs-1.0.0.20.dist-info/METADATA
newWhoisBobPkgs-1.0.0.20.dist-info/WHEEL
newWhoisBobPkgs-1.0.0.20.dist-info/top_level.txt
newWhoisBobPkgs-1.0.0.20.dist-info/RECORD
